{
  "funds": [
    {
      "fundName": "Tech Growth Fund",
      "funCode": "TGF123",
      "security_name": "Apple Inc.",
      "transaction_type": "BUY",
      "order_value": 10000
    },
    {
      "fundName": "Mutual Fund A",
      "funCode": "TGF345",
      "security_name": "Amazon.com, Inc.",
      "transaction_type": "SELL",
      "order_value": 12000
    },
    {
      "fundName": "Global Equity Fund",
      "funCode": "TGF456",
      "security_name": "Caterpillar Inc.",
      "transaction_type": "BUY",
      "order_value": 8000
    }
  ]
}
